{
  "Strings": {
    "AllFilterName": "X",
    "GTEFirstCatName": "FC",
    "MaxProblemsReturned": 5000,
    "TooManyProblemsCode": "TOO_MANY_PROBLEMS"
  },
  "Filters": [
    {
      "Name": "repeats",
      "CSharpAttr": "Repeats",
      "JsonAttr": "Repeats",
      "Type": ">=",
      "Categories": [ 5, 20, 100, 500 ]
    },
    {
      "Name": "rating",
      "CSharpAttr": "Rating",
      "JsonAttr": "Rating",
      "Type": ">=",
      "Categories": [ 1, 2, 3 ]
    },
    {
      "Name": "benchmark",
      "CSharpAttr": "Benchmark",
      "JsonAttr": "IsBenchmark",
      "Type": "boolean"
    },
    {
      "Name": "grade",
      "CSharpAttr": "Grade",
      "JsonAttr": "GradeName",
      "Type": "eq",
      "Categories": [ "V4", "V5", "V6", "V7", "V8", "V9" ]
    }
  ]
}